topsis_sarpreet_101803165/t.py
topsis_sarpreet_101803165-1.0.1.dist-info/LICENSE.txt
topsis_sarpreet_101803165-1.0.1.dist-info/METADATA
topsis_sarpreet_101803165-1.0.1.dist-info/WHEEL
topsis_sarpreet_101803165-1.0.1.dist-info/top_level.txt
topsis_sarpreet_101803165-1.0.1.dist-info/RECORD
