Metadata-Version: 2.1
Name: topsis-sarpreet-101803165
Version: 1.0.1
Summary: TOPSIS MODULE
Home-page: UNKNOWN
Author: sarpreet
Author-email: tiwanasarpreet07@gmail.com
License: MIT
Platform: UNKNOWN
